{"name":"Trello-weekly-report","body":"## Trello Weekly Report generator\r\n### Introduction\r\nA very simple command-line tool that parses a Trello board in JSON format, that I use to create progress reports.\r\n\r\nThis is just a toy project to gain some more experience with Git and Python.\r\n\r\n### How to use it\r\nDownload the sources. Then execute `python create-report.py -f sample.json`\r\n\r\nHere's a more visual explanation: ![Screenshot that shows how simple this is](http://dl.dropbox.com/u/1581166/trello-report-creator.png)\r\n","tagline":"Create a progress report out of a Trello JSON dump","google":"","note":"Don't delete this file! It's used internally to help with page regeneration."}